CHANGELOG.rst
rst_language_server/__init__.py
rst_language_server/__main__.py
rst_language_server/cli.py
rst_language_server/server.py
rst_language_server-0.4.0.dist-info/entry_points.txt
rst_language_server-0.4.0.dist-info/LICENSE
rst_language_server-0.4.0.dist-info/WHEEL
rst_language_server-0.4.0.dist-info/METADATA
rst_language_server-0.4.0.dist-info/RECORD
