Metadata-Version: 2.1
Name: rst-language-server
Version: 0.4.0
Summary: Server implementation of the Language Server Protocol for reStructuredText
Home-page: https://github.com/digitalernachschub/rst-language-server
License: MIT
Author: Michael Seifert
Author-email: m.seifert@digitalernachschub.de
Requires-Python: >=3.7,<4.0
Classifier: Development Status :: 3 - Alpha
Classifier: Environment :: Console
Classifier: License :: OSI Approved :: MIT License
Classifier: Operating System :: OS Independent
Classifier: Programming Language :: Python :: 3
Classifier: Programming Language :: Python :: 3.10
Classifier: Programming Language :: Python :: 3.7
Classifier: Programming Language :: Python :: 3.8
Classifier: Programming Language :: Python :: 3.9
Classifier: Topic :: Text Editors
Requires-Dist: click (>=8.0.3,<9.0.0)
Requires-Dist: docutils (>=0.18,<0.19)
Requires-Dist: pygls (>=0.11.3,<0.12.0)
Project-URL: Repository, https://github.com/digitalernachschub/rst-language-server
